intrusion_monitor/__init__.py
intrusion_monitor/__main__.py
intrusion_monitor/_version.py
intrusion_monitor/api.py
intrusion_monitor/db.py
intrusion_monitor/log_line.py
intrusion_monitor/server.py
intrusion_monitor/utils.py
intrusion_monitor/watchdog.py
test/__init__.py
test/test_api.py
intrusion_monitor-0.1.0.dist-info/LICENSE
intrusion_monitor-0.1.0.dist-info/METADATA
intrusion_monitor-0.1.0.dist-info/WHEEL
intrusion_monitor-0.1.0.dist-info/entry_points.txt
intrusion_monitor-0.1.0.dist-info/top_level.txt
intrusion_monitor-0.1.0.dist-info/RECORD
