Metadata-Version: 2.1
Name: intrusion-monitor
Version: 0.1.0
Summary: An SSH log watchdog, which exports failed login attempts to an InfluxDB timeseries database.
Home-page: https://github.com/afonsoc12/intrusion-monitor
Author: Afonso Costa
License: UNKNOWN
Platform: UNKNOWN
Classifier: Development Status :: 3 - Alpha
Classifier: Programming Language :: Python :: 3
Classifier: License :: OSI Approved :: Apache Software License
Classifier: Operating System :: OS Independent
License-File: LICENSE
Requires-Dist: requests-cache (<1,>=0.9.1)
Requires-Dist: pygeohash (<2,>=1.2.0)
Requires-Dist: influxdb (<6,>=5.3.1)
